_cohere/__init__.py
_cohere/doc_index.py
_cohere/index_documents.py
_google/__init__.py
_google/doc_index.py
_google/index_documents.py
_openai/__init__.py
_openai/doc_index.py
_openai/index_documents.py
tests/__init__.py
tests/cohereindex_test.py
tests/googleindex_test.py
tests/openaiindex_test.py
utils/__init__.py
utils/config.py
utils/create_index.py
utils/delete_index.py
utils/doc_model.py
utils/rerank.py
utils/response_model.py
docindex-0.9.0.dist-info/LICENSE
docindex-0.9.0.dist-info/METADATA
docindex-0.9.0.dist-info/WHEEL
docindex-0.9.0.dist-info/top_level.txt
docindex-0.9.0.dist-info/RECORD
