Metadata-Version: 2.1
Name: docindex
Version: 0.9.0
Summary: A package for fast persistent storage of multiple document embeddings and their metadata into Pinecone for production-level RAG.
Home-page: https://github.com/KevKibe/docindex
Author: Kevin Kibe
Author-email: keviinkibe@gmail.com
License: MIT
Requires-Python: >=3.8
License-File: LICENSE
Requires-Dist: pinecone-client ==3.2.2
Requires-Dist: tiktoken ==0.6.0
Requires-Dist: pypdf ==4.1.0
Requires-Dist: unstructured ==0.12.6
Requires-Dist: langchain-community ==0.0.31
Requires-Dist: langchain ==0.1.14
Requires-Dist: langchain-openai ==0.1.1
Requires-Dist: langchain-google-genai ==1.0.1
Requires-Dist: langchain-pinecone ==0.1.0
Requires-Dist: google.generativeai ==0.4.1
Requires-Dist: python-dotenv ==1.0.1
Requires-Dist: python-docx ==1.1.0
Requires-Dist: markdown ==3.6
Requires-Dist: langchain-core ==0.1.46
Requires-Dist: langchain-cohere ==0.1.4
Requires-Dist: rerankers[all] ==0.2.0
